hdf5eis/__init__.py
hdf5eis/_version.py
hdf5eis/core.py
hdf5eis/exceptions.py
hdf5eis/gather.py
HDF5eis-0.1.1rc2.dist-info/LICENSE
HDF5eis-0.1.1rc2.dist-info/METADATA
HDF5eis-0.1.1rc2.dist-info/WHEEL
HDF5eis-0.1.1rc2.dist-info/top_level.txt
HDF5eis-0.1.1rc2.dist-info/RECORD
