Metadata-Version: 2.1
Name: HDF5eis
Version: 0.1.1rc2
Summary: A solution for handling big, multidimensional timeseries data from environmental sensors in HPC applications.
Home-page: http://malcolmw.github.io/HDF5eis
Download-URL: https://github.com/malcolmw/HDF5eis.git
Author: Malcolm C. A. White
Author-email: "Malcolm C. A. White" <malcolmw@mit.edu>
Maintainer: Malcolm C. A. White
Maintainer-email: malcolmw@mit.edu
Platform: linux
Platform: darwin
Platform: win32
Classifier: Programming Language :: Python :: 3
Classifier: License :: OSI Approved :: MIT License
Classifier: Operating System :: OS Independent
Requires-Python: >=3.6
License-File: LICENSE
Requires-Dist: h5py
Requires-Dist: matplotlib
Requires-Dist: numpy
Requires-Dist: pandas
Requires-Dist: scipy
